cassarrow/__init__.py
cassarrow/impl.py
_cassarrow.cpython-310-x86_64-linux-gnu.so
cassarrow-0.2.0rc4.dist-info/LICENSE
cassarrow-0.2.0rc4.dist-info/WHEEL
cassarrow-0.2.0rc4.dist-info/METADATA
cassarrow-0.2.0rc4.dist-info/RECORD
