Metadata-Version: 2.1
Name: cassarrow
Version: 0.2.0rc4
Summary: Apache Arrow adapter for the Cassandra python driver
Home-page: https://github.com/0x26res/cassarrow
License: Apache-2.0
Keywords: apache-arrow,data
Author: 0x26res
Author-email: 0x26res@gamil.com
Maintainer: 0x26res
Maintainer-email: 0x26res@gmail.com
Requires-Python: >=3.8,<3.11
Classifier: Development Status :: 4 - Beta
Classifier: License :: OSI Approved :: Apache Software License
Classifier: Natural Language :: English
Classifier: Programming Language :: Python :: 3
Classifier: Programming Language :: Python :: 3.8
Classifier: Programming Language :: Python :: 3.9
Classifier: Programming Language :: Python :: 3.10
Classifier: Programming Language :: Python :: 3.10
Classifier: Programming Language :: Python :: 3.8
Classifier: Programming Language :: Python :: 3.9
Requires-Dist: cassandra-driver (>=3.0.0)
Requires-Dist: pyarrow (>=8.0.0)
Requires-Dist: pybind11 (>=2.10.1)
Requires-Dist: wheel (>=0.37.0)
Project-URL: Repository, https://github.com/0x26res/cassarrow
